pydapter/__init__.py
pydapter/async_core.py
pydapter/core.py
pydapter/exceptions.py
pydapter/py.typed
pydapter/types.py
pydapter/adapters/__init__.py
pydapter/adapters/csv_.py
pydapter/adapters/json_.py
pydapter/adapters/toml_.py
pydapter/adapters/yaml_.py
pydapter/extras/README.md
pydapter/extras/__init__.py
pydapter/extras/async_mongo_.py
pydapter/extras/async_neo4j_.py
pydapter/extras/async_postgres_.py
pydapter/extras/async_qdrant_.py
pydapter/extras/async_redis_.py
pydapter/extras/async_sql_.py
pydapter/extras/async_weaviate_.py
pydapter/extras/excel_.py
pydapter/extras/mongo_.py
pydapter/extras/neo4j_.py
pydapter/extras/pandas_.py
pydapter/extras/postgres_.py
pydapter/extras/qdrant_.py
pydapter/extras/sql_.py
pydapter/extras/weaviate_.py
pydapter/migrations/__init__.py
pydapter/migrations/base.py
pydapter/migrations/exceptions.py
pydapter/migrations/protocols.py
pydapter/migrations/registry.py
pydapter/migrations/sql/__init__.py
pydapter/migrations/sql/alembic_adapter.py
pydapter/model_adapters/__init__.py
pydapter/model_adapters/config.py
pydapter/model_adapters/pg_vector_model.py
pydapter/model_adapters/postgres_model.py
pydapter/model_adapters/sql_model.py
pydapter/model_adapters/sql_vector_model.py
pydapter/model_adapters/type_registry.py
pydapter/utils/__init__.py
pydapter/utils/dependencies.py
pydapter-1.2.0.dist-info/METADATA
pydapter-1.2.0.dist-info/WHEEL
pydapter-1.2.0.dist-info/licenses/LICENSE
pydapter-1.2.0.dist-info/RECORD
