Metadata-Version: 2.4
Name: pydapter
Version: 1.2.0
Summary: Tiny trait + adapter toolkit for pydantic models
Author-email: HaiyangLi <quantocean.li@gmail.com>
License-File: LICENSE
Requires-Python: >=3.10
Requires-Dist: orjson>=3.10.0
Requires-Dist: pydantic>=2.6
Requires-Dist: pyyaml>=6.0.0
Requires-Dist: toml>=0.8.0
Requires-Dist: typing-extensions>=4.5.0
Provides-Extra: aiohttp
Requires-Dist: aiohttp>=3.12.0; extra == 'aiohttp'
Provides-Extra: aiosqlite
Requires-Dist: aiosqlite>=0.18.0; extra == 'aiosqlite'
Provides-Extra: all
Requires-Dist: aiohttp>=3.12.0; extra == 'all'
Requires-Dist: aiosqlite>=0.18.0; extra == 'all'
Requires-Dist: alembic>=1.10.0; extra == 'all'
Requires-Dist: asyncpg>=0.28; extra == 'all'
Requires-Dist: email-validator>=2.0.0; extra == 'all'
Requires-Dist: greenlet>=3.0.0; extra == 'all'
Requires-Dist: motor>=3; extra == 'all'
Requires-Dist: neo4j>=5.20; extra == 'all'
Requires-Dist: openpyxl>=3.0.0; extra == 'all'
Requires-Dist: orjson>=3.8.0; extra == 'all'
Requires-Dist: ormsgpack>=1.4.0; extra == 'all'
Requires-Dist: pandas>=2.0; extra == 'all'
Requires-Dist: pgvector>=0.4.0; extra == 'all'
Requires-Dist: psycopg2-binary>=2.8.0; extra == 'all'
Requires-Dist: psycopg[binary]>=3; extra == 'all'
Requires-Dist: pymongo>=4.10; extra == 'all'
Requires-Dist: qdrant-client>=1.10; extra == 'all'
Requires-Dist: redis[hiredis]>=4.2.0; extra == 'all'
Requires-Dist: sqlalchemy[asyncio]>=2.0; extra == 'all'
Requires-Dist: tenacity>=8.0.0; extra == 'all'
Requires-Dist: weaviate-client>=4.10; extra == 'all'
Requires-Dist: weaviate>=0.1.2; extra == 'all'
Requires-Dist: xlsxwriter>=3.2.5; extra == 'all'
Provides-Extra: docs
Requires-Dist: mkdocs-autorefs>=1.4.0; extra == 'docs'
Requires-Dist: mkdocs-material>=9.5.0; extra == 'docs'
Requires-Dist: mkdocs>=1.5.0; extra == 'docs'
Requires-Dist: mkdocstrings[python]>=0.24.0; extra == 'docs'
Requires-Dist: pandas-stubs>=2.2.3; extra == 'docs'
Requires-Dist: pymdown-extensions>=10.7.0; extra == 'docs'
Requires-Dist: types-toml>=0.10.8; extra == 'docs'
Provides-Extra: email
Requires-Dist: email-validator>=2.0.0; extra == 'email'
Provides-Extra: excel
Requires-Dist: openpyxl>=3.0.0; extra == 'excel'
Requires-Dist: pandas>=2.0; extra == 'excel'
Requires-Dist: xlsxwriter>=3.2.5; extra == 'excel'
Provides-Extra: lint
Requires-Dist: bandit>=1.7.5; extra == 'lint'
Requires-Dist: black>=25.1.0; extra == 'lint'
Requires-Dist: isort>=6.0.1; extra == 'lint'
Requires-Dist: pre-commit>=4.2.0; extra == 'lint'
Requires-Dist: ruff>=0.11.11; extra == 'lint'
Provides-Extra: migrations
Requires-Dist: alembic>=1.10.0; extra == 'migrations'
Requires-Dist: sqlalchemy[asyncio]>=2.0; extra == 'migrations'
Provides-Extra: migrations-sql
Requires-Dist: alembic>=1.10.0; extra == 'migrations-sql'
Requires-Dist: sqlalchemy[asyncio]>=2.0; extra == 'migrations-sql'
Provides-Extra: mongo
Requires-Dist: pymongo>=4.10; extra == 'mongo'
Provides-Extra: motor
Requires-Dist: motor>=3; extra == 'motor'
Provides-Extra: neo4j
Requires-Dist: neo4j>=5.20; extra == 'neo4j'
Provides-Extra: pandas
Requires-Dist: pandas>=2.0; extra == 'pandas'
Provides-Extra: performance
Requires-Dist: memory-profiler>=0.61.0; extra == 'performance'
Requires-Dist: py-spy>=0.4.0; extra == 'performance'
Provides-Extra: pgvector
Requires-Dist: asyncpg>=0.28; extra == 'pgvector'
Requires-Dist: greenlet>=3.0.0; extra == 'pgvector'
Requires-Dist: pgvector>=0.4.0; extra == 'pgvector'
Requires-Dist: psycopg2-binary>=2.8.0; extra == 'pgvector'
Requires-Dist: psycopg[binary]>=3; extra == 'pgvector'
Requires-Dist: sqlalchemy[asyncio]>=2.0; extra == 'pgvector'
Provides-Extra: postgres
Requires-Dist: asyncpg>=0.28; extra == 'postgres'
Requires-Dist: greenlet>=3.0.0; extra == 'postgres'
Requires-Dist: psycopg2-binary>=2.8.0; extra == 'postgres'
Requires-Dist: psycopg[binary]>=3; extra == 'postgres'
Requires-Dist: sqlalchemy[asyncio]>=2.0; extra == 'postgres'
Provides-Extra: qdrant
Requires-Dist: qdrant-client>=1.10; extra == 'qdrant'
Provides-Extra: redis
Requires-Dist: orjson>=3.8.0; extra == 'redis'
Requires-Dist: ormsgpack>=1.4.0; extra == 'redis'
Requires-Dist: redis[hiredis]>=4.2.0; extra == 'redis'
Requires-Dist: tenacity>=8.0.0; extra == 'redis'
Provides-Extra: sql
Requires-Dist: sqlalchemy[asyncio]>=2.0; extra == 'sql'
Provides-Extra: test
Requires-Dist: anyio>=4.9.0; extra == 'test'
Requires-Dist: factory-boy>=3.3.0; extra == 'test'
Requires-Dist: faker>=37.3.0; extra == 'test'
Requires-Dist: hypothesis-jsonschema>=0.23.0; extra == 'test'
Requires-Dist: hypothesis>=6.130.0; extra == 'test'
Requires-Dist: mutmut>=3.3.0; extra == 'test'
Requires-Dist: pytest-asyncio>=1.0.0; extra == 'test'
Requires-Dist: pytest-benchmark>=5.0.0; extra == 'test'
Requires-Dist: pytest-cov>=6.0.0; extra == 'test'
Requires-Dist: pytest-mock>=3.10.0; extra == 'test'
Requires-Dist: pytest-timeout>=2.1.0; extra == 'test'
Requires-Dist: pytest-watch>=4.2.0; extra == 'test'
Requires-Dist: pytest-xdist>=3.3.0; extra == 'test'
Requires-Dist: pytest>=8.3.5; extra == 'test'
Requires-Dist: testcontainers[mongodb,postgres,qdrant,redis,weaviate]>=3.7.0; extra == 'test'
Requires-Dist: trio>=0.22.0; extra == 'test'
Provides-Extra: utils
Requires-Dist: colorama>=0.4.0; extra == 'utils'
Requires-Dist: ipykernel>=6.0.0; extra == 'utils'
Requires-Dist: python-dotenv>=1.1.0; extra == 'utils'
Provides-Extra: weaviate
Requires-Dist: weaviate-client>=4.10; extra == 'weaviate'
Requires-Dist: weaviate>=0.1.2; extra == 'weaviate'
